<?xml version="1.0"?>

  <LOCAL host="dwall-0-0.local" >
    <NumPipes value="2" />
    <NumScreens value="2" />
    <NumWindows value="2" />

    <PipeConfig>
      <Pipe server="0" screen="0" name="0" />
      <Pipe server="0" screen="1" name="1" />
    </PipeConfig>

    <ChannelConfig>
      <Channel width="1920" height="1080" left="0" bottom="0" comment="MAIN" stereoMode="MONO"  windowIndex="0"  name="0"  />
      <Channel width="1920" height="1080" left="0" bottom="0" comment="MAIN" stereoMode="MONO"  windowIndex="1"  name="1"  />
    </ChannelConfig>
             
    <WindowConfig>
      <Window width="1920" comment="FRONT" pipeIndex="0" height="1080" left="0" bottom="0" name="0" decoration="false" />
      <Window width="1920" comment="FRONT" pipeIndex="1" height="1080" left="0" bottom="0" name="1" decoration="false" />
    </WindowConfig>

    <ScreenConfig>
      <Screen width="1019" comment="FRONT" h="0.0" originX="-2568" originY="0" originZ="-864" height="568" p="0.0" r="0.0" name="0" />
      <Screen width="1019" comment="FRONT" h="0.0" originX="-1541" originY="0" originZ="-864" height="568" p="0.0" r="0.0" name="1" />
    </ScreenConfig>
  </LOCAL>
  
  <LOCAL host="dwall-0-1.local" >
    <NumPipes value="2" />
    <NumScreens value="2" />
    <NumWindows value="2" />

    <PipeConfig>
      <Pipe server="0" screen="0" name="0" />
      <Pipe server="0" screen="1" name="1" />
    </PipeConfig>

    <ChannelConfig>
      <Channel width="1920" height="1080" left="0" bottom="0" comment="MAIN" stereoMode="MONO"  windowIndex="0"  name="0"  />
      <Channel width="1920" height="1080" left="0" bottom="0" comment="MAIN" stereoMode="MONO"  windowIndex="1"  name="1"  />
    </ChannelConfig>
             
    <WindowConfig>
      <Window width="1920" comment="FRONT" pipeIndex="0" height="1080" left="0" bottom="0" name="0" decoration="false" />
      <Window width="1920" comment="FRONT" pipeIndex="1" height="1080" left="0" bottom="0" name="1" decoration="false" />
    </WindowConfig>

    <ScreenConfig>
      <Screen width="1019" comment="FRONT" h="0.0" originX="-2568" originY="0" originZ="-288" height="568" p="0.0" r="0.0" name="0" />
      <Screen width="1019" comment="FRONT" h="0.0" originX="-1541" originY="0" originZ="-288" height="568" p="0.0" r="0.0" name="1" />
    </ScreenConfig>
  </LOCAL>

  <LOCAL host="dwall-0-2.local" >
    <NumPipes value="2" />
    <NumScreens value="2" />
    <NumWindows value="2" />

    <PipeConfig>
      <Pipe server="0" screen="0" name="0" />
      <Pipe server="0" screen="1" name="1" />
    </PipeConfig>

    <ChannelConfig>
      <Channel width="1920" height="1080" left="0" bottom="0" comment="MAIN" stereoMode="MONO"  windowIndex="0"  name="0"  />
      <Channel width="1920" height="1080" left="0" bottom="0" comment="MAIN" stereoMode="MONO"  windowIndex="1"  name="1"  />
    </ChannelConfig>
             
    <WindowConfig>
      <Window width="1920" comment="FRONT" pipeIndex="0" height="1080" left="0" bottom="0" name="0" decoration="false" />
      <Window width="1920" comment="FRONT" pipeIndex="1" height="1080" left="0" bottom="0" name="1" decoration="false" />
    </WindowConfig>

    <ScreenConfig>
      <Screen width="1019" comment="FRONT" h="0.0" originX="-2568" originY="0" originZ="288" height="568" p="0.0" r="0.0" name="0" />
      <Screen width="1019" comment="FRONT" h="0.0" originX="-1541" originY="0" originZ="288" height="568" p="0.0" r="0.0" name="1" />
    </ScreenConfig>
  </LOCAL>

  <LOCAL host="dwall-0-3.local" >
    <NumPipes value="2" />
    <NumScreens value="2" />
    <NumWindows value="2" />

    <PipeConfig>
      <Pipe server="0" screen="0" name="0" />
      <Pipe server="0" screen="1" name="1" />
    </PipeConfig>

    <ChannelConfig>
      <Channel width="1920" height="1080" left="0" bottom="0" comment="MAIN" stereoMode="MONO"  windowIndex="0"  name="0"  />
      <Channel width="1920" height="1080" left="0" bottom="0" comment="MAIN" stereoMode="MONO"  windowIndex="1"  name="1"  />
    </ChannelConfig>
             
    <WindowConfig>
      <Window width="1920" comment="FRONT" pipeIndex="0" height="1080" left="0" bottom="0" name="0" decoration="false" />
      <Window width="1920" comment="FRONT" pipeIndex="1" height="1080" left="0" bottom="0" name="1" decoration="false" />
    </WindowConfig>

    <ScreenConfig>
      <Screen width="1019" comment="FRONT" h="0.0" originX="-2568" originY="0" originZ="864" height="568" p="0.0" r="0.0" name="0" />
      <Screen width="1019" comment="FRONT" h="0.0" originX="-1541" originY="0" originZ="864" height="568" p="0.0" r="0.0" name="1" />
    </ScreenConfig>
  </LOCAL>

  <LOCAL host="dwall-1-0.local" >
    <NumPipes value="2" />
    <NumScreens value="2" />
    <NumWindows value="2" />

    <PipeConfig>
      <Pipe server="0" screen="0" name="0" />
      <Pipe server="0" screen="1" name="1" />
    </PipeConfig>

    <ChannelConfig>
      <Channel width="1920" height="1080" left="0" bottom="0" comment="MAIN" stereoMode="MONO"  windowIndex="0"  name="0"  />
      <Channel width="1920" height="1080" left="0" bottom="0" comment="MAIN" stereoMode="MONO"  windowIndex="1"  name="1"  />
    </ChannelConfig>
             
    <WindowConfig>
      <Window width="1920" comment="FRONT" pipeIndex="0" height="1080" left="0" bottom="0" name="0" decoration="false" />
      <Window width="1920" comment="FRONT" pipeIndex="1" height="1080" left="0" bottom="0" name="1" decoration="false" />
    </WindowConfig>

    <ScreenConfig>
      <Screen width="1019" comment="FRONT" h="0.0" originX="-514" originY="0" originZ="-864" height="568" p="0.0" r="0.0" name="0" />
      <Screen width="1019" comment="FRONT" h="0.0" originX="514" originY="0" originZ="-864" height="568" p="0.0" r="0.0" name="1" />
    </ScreenConfig>
  </LOCAL>
  
  <LOCAL host="dwall-1-1.local" >
    <NumPipes value="2" />
    <NumScreens value="2" />
    <NumWindows value="2" />

    <PipeConfig>
      <Pipe server="0" screen="0" name="0" />
      <Pipe server="0" screen="1" name="1" />
    </PipeConfig>

    <ChannelConfig>
      <Channel width="1920" height="1080" left="0" bottom="0" comment="MAIN" stereoMode="MONO"  windowIndex="0"  name="0"  />
      <Channel width="1920" height="1080" left="0" bottom="0" comment="MAIN" stereoMode="MONO"  windowIndex="1"  name="1"  />
    </ChannelConfig>
             
    <WindowConfig>
      <Window width="1920" comment="FRONT" pipeIndex="0" height="1080" left="0" bottom="0" name="0" decoration="false" />
      <Window width="1920" comment="FRONT" pipeIndex="1" height="1080" left="0" bottom="0" name="1" decoration="false" />
    </WindowConfig>

    <ScreenConfig>
      <Screen width="1019" comment="FRONT" h="0.0" originX="-514" originY="0" originZ="-288" height="568" p="0.0" r="0.0" name="0" />
      <Screen width="1019" comment="FRONT" h="0.0" originX="514" originY="0" originZ="-288" height="568" p="0.0" r="0.0" name="1" />
    </ScreenConfig>
  </LOCAL>

  <LOCAL host="dwall-1-2.local" >
    <NumPipes value="2" />
    <NumScreens value="2" />
    <NumWindows value="2" />

    <PipeConfig>
      <Pipe server="0" screen="0" name="0" />
      <Pipe server="0" screen="1" name="1" />
    </PipeConfig>

    <ChannelConfig>
      <Channel width="1920" height="1080" left="0" bottom="0" comment="MAIN" stereoMode="MONO"  windowIndex="0"  name="0"  />
      <Channel width="1920" height="1080" left="0" bottom="0" comment="MAIN" stereoMode="MONO"  windowIndex="1"  name="1"  />
    </ChannelConfig>
             
    <WindowConfig>
      <Window width="1920" comment="FRONT" pipeIndex="0" height="1080" left="0" bottom="0" name="0" decoration="false" />
      <Window width="1920" comment="FRONT" pipeIndex="1" height="1080" left="0" bottom="0" name="1" decoration="false" />
    </WindowConfig>

    <ScreenConfig>
      <Screen width="1019" comment="FRONT" h="0.0" originX="-514" originY="0" originZ="288" height="568" p="0.0" r="0.0" name="0" />
      <Screen width="1019" comment="FRONT" h="0.0" originX="514" originY="0" originZ="288" height="568" p="0.0" r="0.0" name="1" />
    </ScreenConfig>
  </LOCAL>

  <LOCAL host="dwall-1-3.local" >
    <NumPipes value="2" />
    <NumScreens value="2" />
    <NumWindows value="2" />

    <PipeConfig>
      <Pipe server="0" screen="0" name="0" />
      <Pipe server="0" screen="1" name="1" />
    </PipeConfig>

    <ChannelConfig>
      <Channel width="1920" height="1080" left="0" bottom="0" comment="MAIN" stereoMode="MONO"  windowIndex="0"  name="0"  />
      <Channel width="1920" height="1080" left="0" bottom="0" comment="MAIN" stereoMode="MONO"  windowIndex="1"  name="1"  />
    </ChannelConfig>
             
    <WindowConfig>
      <Window width="1920" comment="FRONT" pipeIndex="0" height="1080" left="0" bottom="0" name="0" decoration="false" />
      <Window width="1920" comment="FRONT" pipeIndex="1" height="1080" left="0" bottom="0" name="1" decoration="false" />
    </WindowConfig>

    <ScreenConfig>
      <Screen width="1019" comment="FRONT" h="0.0" originX="-514" originY="0" originZ="864" height="568" p="0.0" r="0.0" name="0" />
      <Screen width="1019" comment="FRONT" h="0.0" originX="514" originY="0" originZ="864" height="568" p="0.0" r="0.0" name="1" />
    </ScreenConfig>
  </LOCAL>

  <LOCAL host="dwall-2-0.local" >
    <NumPipes value="2" />
    <NumScreens value="2" />
    <NumWindows value="2" />

    <PipeConfig>
      <Pipe server="0" screen="0" name="0" />
      <Pipe server="0" screen="1" name="1" />
    </PipeConfig>

    <ChannelConfig>
      <Channel width="1920" height="1080" left="0" bottom="0" comment="MAIN" stereoMode="MONO"  windowIndex="0"  name="0"  />
      <Channel width="1920" height="1080" left="0" bottom="0" comment="MAIN" stereoMode="MONO"  windowIndex="1"  name="1"  />
    </ChannelConfig>
             
    <WindowConfig>
      <Window width="1920" comment="FRONT" pipeIndex="0" height="1080" left="0" bottom="0" name="0" decoration="false" />
      <Window width="1920" comment="FRONT" pipeIndex="1" height="1080" left="0" bottom="0" name="1" decoration="false" />
    </WindowConfig>

    <ScreenConfig>
      <Screen width="1019" comment="FRONT" h="0.0" originX="1541" originY="0" originZ="-864" height="568" p="0.0" r="0.0" name="0" />
      <Screen width="1019" comment="FRONT" h="0.0" originX="2568" originY="0" originZ="-864" height="568" p="0.0" r="0.0" name="1" />
    </ScreenConfig>
  </LOCAL>
  
  <LOCAL host="dwall-2-1.local" >
    <NumPipes value="2" />
    <NumScreens value="2" />
    <NumWindows value="2" />

    <PipeConfig>
      <Pipe server="0" screen="0" name="0" />
      <Pipe server="0" screen="1" name="1" />
    </PipeConfig>

    <ChannelConfig>
      <Channel width="1920" height="1080" left="0" bottom="0" comment="MAIN" stereoMode="MONO"  windowIndex="0"  name="0"  />
      <Channel width="1920" height="1080" left="0" bottom="0" comment="MAIN" stereoMode="MONO"  windowIndex="1"  name="1"  />
    </ChannelConfig>
             
    <WindowConfig>
      <Window width="1920" comment="FRONT" pipeIndex="0" height="1080" left="0" bottom="0" name="0" decoration="false" />
      <Window width="1920" comment="FRONT" pipeIndex="1" height="1080" left="0" bottom="0" name="1" decoration="false" />
    </WindowConfig>

    <ScreenConfig>
      <Screen width="1019" comment="FRONT" h="0.0" originX="1541" originY="0" originZ="-288" height="568" p="0.0" r="0.0" name="0" />
      <Screen width="1019" comment="FRONT" h="0.0" originX="2568" originY="0" originZ="-288" height="568" p="0.0" r="0.0" name="1" />
    </ScreenConfig>
  </LOCAL>

  <LOCAL host="dwall-2-2.local" >
    <NumPipes value="2" />
    <NumScreens value="2" />
    <NumWindows value="2" />

    <PipeConfig>
      <Pipe server="0" screen="0" name="0" />
      <Pipe server="0" screen="1" name="1" />
    </PipeConfig>

    <ChannelConfig>
      <Channel width="1920" height="1080" left="0" bottom="0" comment="MAIN" stereoMode="MONO"  windowIndex="0"  name="0"  />
      <Channel width="1920" height="1080" left="0" bottom="0" comment="MAIN" stereoMode="MONO"  windowIndex="1"  name="1"  />
    </ChannelConfig>
             
    <WindowConfig>
      <Window width="1920" comment="FRONT" pipeIndex="0" height="1080" left="0" bottom="0" name="0" decoration="false" />
      <Window width="1920" comment="FRONT" pipeIndex="1" height="1080" left="0" bottom="0" name="1" decoration="false" />
    </WindowConfig>

    <ScreenConfig>
      <Screen width="1019" comment="FRONT" h="0.0" originX="1541" originY="0" originZ="288" height="568" p="0.0" r="0.0" name="0" />
      <Screen width="1019" comment="FRONT" h="0.0" originX="2568" originY="0" originZ="288" height="568" p="0.0" r="0.0" name="1" />
    </ScreenConfig>
  </LOCAL>

  <LOCAL host="dwall-2-3.local" >
    <NumPipes value="2" />
    <NumScreens value="2" />
    <NumWindows value="2" />

    <PipeConfig>
      <Pipe server="0" screen="0" name="0" />
      <Pipe server="0" screen="1" name="1" />
    </PipeConfig>

    <ChannelConfig>
      <Channel width="1920" height="1080" left="0" bottom="0" comment="MAIN" stereoMode="MONO"  windowIndex="0"  name="0"  />
      <Channel width="1920" height="1080" left="0" bottom="0" comment="MAIN" stereoMode="MONO"  windowIndex="1"  name="1"  />
    </ChannelConfig>
             
    <WindowConfig>
      <Window width="1920" comment="FRONT" pipeIndex="0" height="1080" left="0" bottom="0" name="0" decoration="false" />
      <Window width="1920" comment="FRONT" pipeIndex="1" height="1080" left="0" bottom="0" name="1" decoration="false" />
    </WindowConfig>

    <ScreenConfig>
      <Screen width="1019" comment="FRONT" h="0.0" originX="1541" originY="0" originZ="864" height="568" p="0.0" r="0.0" name="0" />
      <Screen width="1019" comment="FRONT" h="0.0" originX="2568" originY="0" originZ="864" height="568" p="0.0" r="0.0" name="1" />
    </ScreenConfig>
  </LOCAL>
